{"is_source_file": true, "format": "Kotlin", "description": "This file defines the SearchFragment class, which implements a search UI optimized for Android TV DPAD navigation. It includes keyboard input handling, displaying search results, managing user interaction, and communicating with a host activity.", "external_files": ["R (resource layout: R.layout.fragment_search)", "com.example.frontend_android_tv_app.R", "ProgressStore", "FavoritesStore", "RecentSearchesStore", "Video", "VideoSearchIndex", "VideosRepository", "KeyboardAdapter", "KeyboardKey", "SearchResultsAdapter"], "external_methods": ["ProgressStore.from()", "FavoritesStore.from()", "RecentSearchesStore.from()", "VideoSearchIndex.search()", "VideosRepository.videosForCategory()", "VideosRepository.categories"], "published": [" SearchFragment"], "classes": [{"name": "SearchFragment", "description": "A Fragment representing a search screen with a custom on-screen keyboard and search results grid, designed for Android TV DPAD navigation."}], "methods": [{"name": "onCreateView", "description": "Inflates the fragment layout from XML."}, {"name": "onViewCreated", "description": "Initializes the Stores, views, adapters, and sets up key navigation."}, {"name": "setupKeyboard", "description": "Sets up the on-screen keyboard with keys, layout manager, and focus behavior."}, {"name": "setupResults", "description": "Sets up the search results grid and focus handling."}, {"name": "buildKeyboardKeys", "description": "Creates a list of keyboard keys including letters, numbers, and function keys."}, {"name": "onKeyboardKeyPressed", "description": "Handles input from the keyboard, updating the query or performing actions."}, {"name": "applyBackspace", "description": "Removes the last character from the query and updates display and results."}, {"name": "renderQuery", "description": "Displays the current query text and updates accessibility content descriptions."}, {"name": "updateResults", "description": "Fetches search results based on the current query and updates the results adapter."}], "calls": ["ProgressStore.from", "FavoritesStore.from", "RecentSearchesStore.from", "VideoSearchIndex.search", "VideosRepository.videosForCategory", "ResultsAdapter.submitList", "keyboardRecycler.requestFocus", "resultsRecycler.requestFocus", "recentSearchesStore.push", "activity?.openDetails", "activity?.goBack"], "search-terms": ["SearchFragment", "Android TV", "DPAD", "on-screen keyboard", "search results grid", "KeyboardKey", "focus navigation"], "state": 2, "file_id": 44, "knowledge_revision": 154, "git_revision": "aa58702dc5379952f4b1da5310ab2da8412306d0", "revision_history": [{"122": "aa58702dc5379952f4b1da5310ab2da8412306d0"}, {"154": "aa58702dc5379952f4b1da5310ab2da8412306d0"}], "hash": "c0266593b48d97b170cee3a9236228b3", "format-version": 4, "code-base-name": "frontend_android_tv_app", "filename": "frontend_android_tv_app/app/src/main/java/com/example/frontend_android_tv_app/ui/screens/SearchFragment.kt"}